MANIFEST.in
README.rst
setup.py
stocky/__init__.py
stocky/__main__.py
stocky/stocky.py
stocky.egg-info/PKG-INFO
stocky.egg-info/SOURCES.txt
stocky.egg-info/dependency_links.txt
stocky.egg-info/entry_points.txt
stocky.egg-info/top_level.txt