Metadata-Version: 1.0
Name: stocky
Version: 0.0.1.dev0
Summary: a program to track stocks and other finacial via terminal
Home-page: https://github.com/ejmg/stocky
Author: elias julian marko garcia
Author-email: elias.jm.garcia@gmail.com
License: MIT
Platform: UNKNOWN
